recommendation_engine_client/__init__.py
recommendation_engine_client/client.py
recommendation_engine_client/exceptions.py
recommendation_engine_client/types.py
recommendation_engine_client-1.0.1.dist-info/WHEEL
recommendation_engine_client-1.0.1.dist-info/METADATA
recommendation_engine_client-1.0.1.dist-info/RECORD
