Metadata-Version: 2.3
Name: recommendation-engine-client
Version: 1.0.1
Summary: Python client library for the GrooveShop Recommendation Engine
Keywords: recommendation,recommendation-engine,machine-learning,collaborative-filtering,content-based-filtering,python,httpx,async
Author: GrooveShop Team
Author-email: GrooveShop Team <support@grooveshop.com>
License: MIT
Classifier: Development Status :: 5 - Production/Stable
Classifier: Intended Audience :: Developers
Classifier: License :: OSI Approved :: MIT License
Classifier: Programming Language :: Python :: 3
Classifier: Programming Language :: Python :: 3.13
Classifier: Programming Language :: Python :: 3.14
Classifier: Programming Language :: Python :: 3 :: Only
Classifier: Typing :: Typed
Requires-Dist: httpx==0.28.1
Requires-Dist: typing-extensions==4.15.0
Requires-Dist: pytest==8.4.2 ; extra == 'dev'
Requires-Dist: pytest-asyncio==1.2.0 ; extra == 'dev'
Requires-Dist: pytest-cov==7.0.0 ; extra == 'dev'
Requires-Dist: pytest-httpx==0.35.0 ; extra == 'dev'
Requires-Dist: ruff==0.14.1 ; extra == 'dev'
Requires-Dist: mypy==1.18.2 ; extra == 'dev'
Requires-Python: >=3.13
Project-URL: Documentation, https://docs.grooveshop.com/recommendation-engine
Project-URL: Homepage, https://github.com/grooveshop/recommendation-engine
Project-URL: Issues, https://github.com/grooveshop/recommendation-engine/issues
Project-URL: Repository, https://github.com/grooveshop/recommendation-engine
Provides-Extra: dev
